{
  "component": {
    "tag": {
      "default": {
        "background": {
          "value": "{alias.interaction.background.secondary}",
          "type": "color"
        },
        "border": {
          "value": "{alias.interaction.border.default}",
          "type": "color"
        },
        "text": {
          "value": "{alias.content.text.primary.default}",
          "type": "color"
        },
        "icon": {
          "default": {
            "value": "{alias.content.icon.primary.default}",
            "type": "color"
          },
          "hover": {
            "value": "{alias.content.icon.primary.hover}",
            "type": "color"
          },
          "active": {
            "value": "{alias.content.icon.primary.active}",
            "type": "color"
          }
        }
      },
      "hover": {
        "background": {
          "value": "{alias.interaction.background.secondary}",
          "type": "color"
        },
        "border": {
          "value": "{alias.interaction.border.hover}",
          "type": "color"
        },
        "text": {
          "value": "{alias.content.text.primary.default}",
          "type": "color"
        },
        "icon": {
          "default": {
            "value": "{alias.content.icon.primary.default}",
            "type": "color"
          },
          "hover": {
            "value": "{alias.content.icon.primary.hover}",
            "type": "color"
          },
          "active": {
            "value": "{alias.content.icon.primary.active}",
            "type": "color"
          }
        }
      },
      "focus": {
        "background": {
          "value": "{alias.interaction.background.tertiary}",
          "type": "color"
        },
        "border": {
          "value": "{alias.interaction.border.focus}",
          "type": "color"
        },
        "text": {
          "value": "{alias.content.text.primary.default}",
          "type": "color"
        },
        "icon": {
          "default": {
            "value": "{alias.content.icon.primary.default}",
            "type": "color"
          },
          "hover": {
            "value": "{alias.content.icon.primary.hover}",
            "type": "color"
          },
          "active": {
            "value": "{alias.content.icon.primary.active}",
            "type": "color"
          }
        }
      },
      "error": {
        "background": {
          "value": "{alias.interaction.background.secondary}",
          "type": "color"
        },
        "border": {
          "value": "{alias.interaction.border.error}",
          "type": "color"
        },
        "text": {
          "value": "{alias.content.text.primary.default}",
          "type": "color"
        },
        "icon": {
          "default": {
            "value": "{alias.content.icon.primary.default}",
            "type": "color"
          },
          "hover": {
            "value": "{alias.content.icon.primary.hover}",
            "type": "color"
          },
          "active": {
            "value": "{alias.content.icon.primary.active}",
            "type": "color"
          }
        }
      },
      "disabled": {
        "background": {
          "value": "{alias.interaction.background.disabled}",
          "type": "color"
        },
        "border": {
          "value": "{alias.interaction.border.disabled}",
          "type": "color"
        },
        "text": {
          "value": "{alias.content.text.primary.disabled}",
          "type": "color"
        },
        "icon": {
          "default": {
            "value": "{alias.content.icon.primary.disabled}",
            "type": "color"
          }
        }
      },
      "readOnly": {
        "background": {
          "value": "{alias.interaction.background.primary}",
          "type": "color"
        },
        "border": {
          "value": "{alias.interaction.border.disabled}",
          "type": "color"
        },
        "text": {
          "value": "{alias.content.text.primary.default}",
          "type": "color"
        },
        "icon": {
          "default": {
            "value": "{alias.content.icon.primary.default}",
            "type": "color"
          }
        }
      }
    }
  }
}